captif_db_config/__init__.py
captif_db_config-0.14.dist-info/LICENSE
captif_db_config-0.14.dist-info/METADATA
captif_db_config-0.14.dist-info/WHEEL
captif_db_config-0.14.dist-info/RECORD
